{
  "kind": "coverage_report",
  "version": "1.0",
  "generatedAt": "2026-02-21T14:27:06.752Z",
  "sources": {
    "buildRequest": true,
    "implementationPlan": true
  },
  "requirements": {
    "total": 4,
    "implemented": 0,
    "items": [
      {
        "id": "REQ-1",
        "summary": "Add an in-memory session buffer for each logged-in INVESTOR that stores exactly the last 6 txn_hash values for that investor's current session, scoped per user session and not global",
        "status": "unknown",
        "plannedFiles": [],
        "matchedFiles": []
      },
      {
        "id": "REQ-2",
        "summary": "When a new Transaction is created, append its txn_hash into the investor's session buffer, implementing FIFO ring buffer behavior where if the buffer already has 6 hashes, remove the oldest and then add the new one",
        "status": "unknown",
        "plannedFiles": [],
        "matchedFiles": []
      },
      {
        "id": "REQ-3",
        "summary": "Add a read-only backend endpoint that returns the current list of up to 6 transaction hashes for the logged-in investor, ordered from oldest to newest",
        "status": "unknown",
        "plannedFiles": [],
        "matchedFiles": []
      },
      {
        "id": "REQ-4",
        "summary": "Display the code or logic added for the session buffer and read-only endpoint in the implementation",
        "status": "unknown",
        "plannedFiles": [],
        "matchedFiles": []
      }
    ]
  },
  "changedFiles": [
    "backend/main.mo",
    "build-request.json",
    "feature_evidence.json",
    "frontend-file-summaries.txt",
    "frontend-implementation-plan.json",
    "frontend/src/backend.d.ts",
    "frontend/src/backend.ts",
    "frontend/src/components/Dashboard.tsx",
    "frontend/src/declarations/backend.did.d.ts",
    "frontend/src/declarations/backend.did.js",
    "frontend/src/hooks/useQueries.ts",
    "project_state.json",
    "scratch/component-selection.json",
    "spec.md",
    "spec_vs_diff_report.json"
  ]
}